aixplain/model_interfaces/__init__.py
aixplain/model_interfaces/__version__.py
aixplain/model_interfaces/interfaces/__init__.py
aixplain/model_interfaces/interfaces/aixplain_metric.py
aixplain/model_interfaces/interfaces/aixplain_model.py
aixplain/model_interfaces/interfaces/aixplain_model_server.py
aixplain/model_interfaces/interfaces/asset_resolver.py
aixplain/model_interfaces/interfaces/function_models.py
aixplain/model_interfaces/interfaces/metric_models.py
aixplain/model_interfaces/interfaces/project_node.py
aixplain/model_interfaces/interfaces/metric_server/__init__.py
aixplain/model_interfaces/interfaces/metric_server/aixplain_metric_server.py
aixplain/model_interfaces/interfaces/metric_server/dataplane.py
aixplain/model_interfaces/interfaces/metric_server/metric_errors.py
aixplain/model_interfaces/interfaces/metric_server/rest_server.py
aixplain/model_interfaces/interfaces/metric_server/v1_endpoints.py
aixplain/model_interfaces/schemas/__init__.py
aixplain/model_interfaces/schemas/api/basic_api_input.py
aixplain/model_interfaces/schemas/api/basic_api_output.py
aixplain/model_interfaces/schemas/function/function_input.py
aixplain/model_interfaces/schemas/function/function_output.py
aixplain/model_interfaces/schemas/metric/metric_input.py
aixplain/model_interfaces/schemas/metric/metric_output.py
aixplain/model_interfaces/schemas/modality/modality_input.py
aixplain/model_interfaces/schemas/modality/modality_output.py
aixplain/model_interfaces/schemas/script/script_input.py
aixplain/model_interfaces/schemas/script/script_output.py
aixplain/model_interfaces/utils/__init__.py
aixplain/model_interfaces/utils/data_utils.py
aixplain/model_interfaces/utils/metric_utils.py
aixplain/model_interfaces/utils/serialize.py
model_interfaces-1.1.0.dist-info/METADATA
model_interfaces-1.1.0.dist-info/WHEEL
model_interfaces-1.1.0.dist-info/top_level.txt
model_interfaces-1.1.0.dist-info/RECORD
