Metadata-Version: 2.4
Name: model-interfaces
Version: 1.1.0
Summary: A package specifying the model interfaces supported by aiXplain
License: Apache License, Version 2.0: http://www.apache.org/licenses/LICENSE-2.0
Project-URL: Homepage, https://github.com/aixplain/model-interfaces
Requires-Dist: kserve>=0.10.0
Requires-Dist: multiprocess==0.70.14
Requires-Dist: protobuf>=3.19.4
Requires-Dist: pyarrow==17.0.0
Requires-Dist: pydantic<3.0.0,>=2.0.0
Requires-Dist: pydub>=0.25.1
Requires-Dist: requests>=2.28.1
Requires-Dist: tornado>=6.2
Requires-Dist: validators>=0.20.0
Provides-Extra: test
Requires-Dist: pytest>=7.1.2; extra == "test"
Requires-Dist: sentencepiece>=0.1.96; extra == "test"
Requires-Dist: torch>=1.13.1; extra == "test"
Requires-Dist: transformers>=4.21.1; extra == "test"
